_link.cpython-313-arm-linux-gnueabihf.so
link/__init__.py
link/__init__.pyi
link/py.typed
linkpython_extern-1.2.1.dist-info/METADATA
linkpython_extern-1.2.1.dist-info/WHEEL
linkpython_extern-1.2.1.dist-info/top_level.txt
linkpython_extern-1.2.1.dist-info/RECORD
linkpython_extern-1.2.1.dist-info/licenses/LICENSE.md
