Metadata-Version: 2.1
Name: LinkPython-extern
Version: 1.2.1
Summary: A fork of the LinkPython wrapper for Ableton Link
Author: gonzaloflirt
Maintainer: thegamecracks
License: Unlicense
Project-URL: Homepage, https://github.com/thegamecracks/link-python
Classifier: Development Status :: 5 - Production/Stable
Classifier: Intended Audience :: Developers
Classifier: Programming Language :: C++
Classifier: Programming Language :: Python
Classifier: Topic :: System :: Networking
Requires-Python: <3.15,>=3.8
License-File: LICENSE.md
